[
  {
    "link_it": "https://github.com/lmbstudiocontact/cb_1000_it_1/raw/main/rise_cb_1000_it.json",
    "id_item": "rise_cb_1000_it",
    "id_album": "102079921",
    "english": "rise",
    "list_mean": [
      "tăng lên; mọc lên",
      "chuyển động lên trên",
      "thức dậy",
      "đứng dậy",
      "mọc (mặt trời)",
      "trải dài lên phía trên",
      "nổi loạn",
      "thăng chức",
      "xuất hiện",
      "thổi mạnh",
      "đang được xây dựng",
      "hồi sinh",
      "sự tăng lên",
      "sự tăng lương",
      "sườn dốc",
      "sự nổi lên"
    ],
    "cau_en": "",
    "cau_vn": "",
    "hash_code_list_mean": "1531668194"
  },
  {
    "link_it": "https://github.com/lmbstudiocontact/cb_1000_it_1/raw/main/river_cb_1000_it.json",
    "id_item": "river_cb_1000_it",
    "id_album": "102079921",
    "english": "river",
    "list_mean": [
      "dòng sông"
    ],
    "cau_en": "",
    "cau_vn": "",
    "hash_code_list_mean": "-1975304782"
  },
  {
    "link_it": "https://github.com/lmbstudiocontact/cb_1000_it_1/raw/main/roadside_cb_1000_it.json",
    "id_item": "roadside_cb_1000_it",
    "id_album": "102079921",
    "english": "roadside",
    "list_mean": [
      "hè phố"
    ],
    "cau_en": "",
    "cau_vn": "",
    "hash_code_list_mean": "-1102206632"
  },
  {
    "link_it": "https://github.com/lmbstudiocontact/cb_1000_it_1/raw/main/road_cb_1000_it.json",
    "id_item": "road_cb_1000_it",
    "id_album": "102079921",
    "english": "road",
    "list_mean": [
      "đường giao thông",
      "phố",
      "tuyến đường",
      "con đường dẫn tới"
    ],
    "cau_en": "",
    "cau_vn": "",
    "hash_code_list_mean": "489752748"
  },
  {
    "link_it": "https://github.com/lmbstudiocontact/cb_1000_it_1/raw/main/rock_cb_1000_it.json",
    "id_item": "rock_cb_1000_it",
    "id_album": "102079921",
    "english": "rock",
    "list_mean": [
      "đá",
      "đá tảng",
      "thanh kẹo cứng",
      "đung đưa",
      "đung đưa cho cho một đứa bé ngủ trên tay",
      "lắc mạnh",
      "nhạc rốc"
    ],
    "cau_en": "",
    "cau_vn": "",
    "hash_code_list_mean": "-1403680098"
  },
  {
    "link_it": "https://github.com/lmbstudiocontact/cb_1000_it_1/raw/main/roll_cb_1000_it.json",
    "id_item": "roll_cb_1000_it",
    "id_album": "102079921",
    "english": "roll",
    "list_mean": [
      "súc; cuộn",
      "ổ bánh mỳ nhỏ",
      "sự cuộn mình",
      "sự lắc lư",
      "tiếng sấm vang rền",
      "lằn thịt",
      "những hồi trống",
      "lăn",
      "đẩy; lăn",
      "cuộn thành ống",
      "cuộn; đẩy",
      "nặn",
      "quấn",
      "làm phẳng",
      "lắc lư",
      "tiếng vang rền",
      "trợn tròn mắt",
      "đi du lịch bằng xe hơi",
      "sóng cuồn cuộn",
      "trôi qua",
      "danh sách"
    ],
    "cau_en": "",
    "cau_vn": "",
    "hash_code_list_mean": "80267996"
  },
  {
    "link_it": "https://github.com/lmbstudiocontact/cb_1000_it_1/raw/main/romantic_cb_1000_it.json",
    "id_item": "romantic_cb_1000_it",
    "id_album": "102079921",
    "english": "romantic",
    "list_mean": [
      "thuộc lãng mạn",
      "có tính lãng mạn",
      "mơ mộng",
      "người bay bổng",
      "người lãng mạn",
      "nhà văn, nhà thơ lãng mạn"
    ],
    "cau_en": "",
    "cau_vn": "",
    "hash_code_list_mean": "1785747090"
  },
  {
    "link_it": "https://github.com/lmbstudiocontact/cb_1000_it_1/raw/main/room_cb_1000_it.json",
    "id_item": "room_cb_1000_it",
    "id_album": "102079921",
    "english": "room",
    "list_mean": [
      "phòng",
      "nơi chỗ",
      "sự cần thiết"
    ],
    "cau_en": "",
    "cau_vn": "",
    "hash_code_list_mean": "-761702212"
  },
  {
    "link_it": "https://github.com/lmbstudiocontact/cb_1000_it_1/raw/main/root_cb_1000_it.json",
    "id_item": "root_cb_1000_it",
    "id_album": "102079921",
    "english": "root",
    "list_mean": [
      "rễ cây",
      "chân tóc; chân răng",
      "nguồn gốc",
      "tổ tiên",
      "làm bắt rễ",
      "dũi đất",
      "sục sạo"
    ],
    "cau_en": "",
    "cau_vn": "",
    "hash_code_list_mean": "-441605978"
  },
  {
    "link_it": "https://github.com/lmbstudiocontact/cb_1000_it_1/raw/main/rope_cb_1000_it.json",
    "id_item": "rope_cb_1000_it",
    "id_album": "102079921",
    "english": "rope",
    "list_mean": [
      "dây chão",
      "buộc bằng dây chão",
      "bắt bằng dây thòng lọng"
    ],
    "cau_en": "",
    "cau_vn": "",
    "hash_code_list_mean": "149331313"
  },
  {
    "link_it": "https://github.com/lmbstudiocontact/cb_1000_it_1/raw/main/roundabout_cb_1000_it.json",
    "id_item": "roundabout_cb_1000_it",
    "id_album": "102079921",
    "english": "roundabout",
    "list_mean": [
      "chỗ đường vòng",
      "vòng ngựa gỗ cho trẻ em",
      "thuộc vòng"
    ],
    "cau_en": "",
    "cau_vn": "",
    "hash_code_list_mean": "791982128"
  },
  {
    "link_it": "https://github.com/lmbstudiocontact/cb_1000_it_1/raw/main/round_cb_1000_it.json",
    "id_item": "round_cb_1000_it",
    "id_album": "102079921",
    "english": "round",
    "list_mean": [
      "tròn",
      "bụ bẫm",
      "theo chiều ngược lại",
      "vòng tròn",
      "theo vòng tròn",
      "đi một vòng",
      "chu vi",
      "tới thăm một gia đình",
      "xung quanh",
      "vòng quanh",
      "hướng về",
      "khắp nơi",
      "sự quay vòng",
      "chuyến đi",
      "sự tán thưởng",
      "viên đạn",
      "vòng thi đấu",
      "ca nông (âm nhạc)",
      "đi vòng quanh"
    ],
    "cau_en": "",
    "cau_vn": "",
    "hash_code_list_mean": "-2048691082"
  },
  {
    "link_it": "https://github.com/lmbstudiocontact/cb_1000_it_1/raw/main/row_cb_1000_it.json",
    "id_item": "row_cb_1000_it",
    "id_album": "102079921",
    "english": "row",
    "list_mean": [
      "hàng; dãy",
      "chèo thuyền",
      "chèo thuyền chở khách",
      "chuyến đi bằng thuyền",
      "cuộc cãi vã",
      "sự huyên náo"
    ],
    "cau_en": "",
    "cau_vn": "",
    "hash_code_list_mean": "1035432633"
  },
  {
    "link_it": "https://github.com/lmbstudiocontact/cb_1000_it_1/raw/main/rub_cb_1000_it.json",
    "id_item": "rub_cb_1000_it",
    "id_album": "102079921",
    "english": "rub",
    "list_mean": [
      "cọ; rụi",
      "sự cọ; cái rụi"
    ],
    "cau_en": "",
    "cau_vn": "",
    "hash_code_list_mean": "749932938"
  },
  {
    "link_it": "https://github.com/lmbstudiocontact/cb_1000_it_1/raw/main/rude_cb_1000_it.json",
    "id_item": "rude_cb_1000_it",
    "id_album": "102079921",
    "english": "rude",
    "list_mean": [
      "thô lỗ",
      "thiếu thẩm mỹ"
    ],
    "cau_en": "",
    "cau_vn": "",
    "hash_code_list_mean": "-198598475"
  },
  {
    "link_it": "https://github.com/lmbstudiocontact/cb_1000_it_1/raw/main/rule_cb_1000_it.json",
    "id_item": "rule_cb_1000_it",
    "id_album": "102079921",
    "english": "rule",
    "list_mean": [
      "sự thống trị",
      "quy tắc",
      "lệ thường",
      "nguyên tắc",
      "thước đo",
      "cai trị",
      "phán quyết",
      "kẻ dòng"
    ],
    "cau_en": "",
    "cau_vn": "",
    "hash_code_list_mean": "779132397"
  },
  {
    "link_it": "https://github.com/lmbstudiocontact/cb_1000_it_1/raw/main/running_cb_1000_it.json",
    "id_item": "running_cb_1000_it",
    "id_album": "102079921",
    "english": "running",
    "list_mean": [
      "để chạy",
      "tiếp tục",
      "nối tiếp"
    ],
    "cau_en": "",
    "cau_vn": "",
    "hash_code_list_mean": "2073297426"
  },
  {
    "link_it": "https://github.com/lmbstudiocontact/cb_1000_it_1/raw/main/run_cb_1000_it.json",
    "id_item": "run_cb_1000_it",
    "id_album": "102079921",
    "english": "run",
    "list_mean": [
      "chạy",
      "hoạt động",
      "chảy",
      "vận hành",
      "điều hành",
      "chạy đua",
      "chạy theo lộ trình",
      "kéo dài",
      "lái",
      "phai màu",
      "chở ai đi đâu; cho ai đi nhờ xe",
      "luồn, lướt",
      "trở nên",
      "sự chạy",
      "cuộc tham quan",
      "thời gian liên tục",
      "kẽ hở ở bít tất",
      "sự cho phép sử dụng",
      "ghi điểm trong môn crickit",
      "sân nuôi gà, vịt; bãi rào kín"
    ],
    "cau_en": "",
    "cau_vn": "",
    "hash_code_list_mean": "711290876"
  }
]